easy_mining/__init__.py
easy_mining/exploration/__init__.py
easy_mining/exploration/common.py
easy_mining/processing/__init__.py
easy_mining/processing/common.py
easy_mining/processing/date.py
easy_mining/recommendation/__init__.py
easy_mining/recommendation/metrics.py
tests/__init__.py
tests/exploration/__init__.py
tests/exploration/test_common.py
tests/processing/__init__.py
tests/processing/test_date.py
easy_mining-0.0.8.dist-info/LICENSE
easy_mining-0.0.8.dist-info/METADATA
easy_mining-0.0.8.dist-info/WHEEL
easy_mining-0.0.8.dist-info/top_level.txt
easy_mining-0.0.8.dist-info/RECORD
