Metadata-Version: 2.1
Name: easy-mining
Version: 0.0.8
Summary: An easy way of data mining.
Home-page: https://github.com/Noluye/easy_mining
Author: Noluye
Author-email: 1183851628@qq.com
License: UNKNOWN
Platform: UNKNOWN
Classifier: Programming Language :: Python :: 3
Classifier: License :: OSI Approved :: MIT License
Classifier: Operating System :: OS Independent
